{ "data": [ { "_id": "2013-10-16T11:10:03+01:00", "_month_start_at": "2013-10-01T00:00:00", "_timestamp": "2013-10-16T10:10:03+00:00", "_updated_at": "2013-10-16T11:10:03.451000", "_week_start_at": "2013-10-14T00:00:00", "for_url": "ga:pagePath=~^/tax-disc$", "unique_visitors": "496" }, { "_id": "2013-10-16T11:08:03+01:00", "_month_start_at": "2013-10-01T00:00:00", "_timestamp": "2013-10-16T10:08:03+00:00", "_updated_at": "2013-10-16T11:08:03.046000", "_week_start_at": "2013-10-14T00:00:00", "for_url": "ga:pagePath=~^/tax-disc$", "unique_visitors": "468" }, { "_id": "2013-10-16T11:06:02+01:00", "_month_start_at": "2013-10-01T00:00:00", "_timestamp": "2013-10-16T10:06:02+00:00", "_updated_at": "2013-10-16T11:06:03.440000", "_week_start_at": "2013-10-14T00:00:00", "for_url": "ga:pagePath=~^/tax-disc$", "unique_visitors": "513" }, { "_id": "2013-10-16T11:04:04+01:00", "_month_start_at": "2013-10-01T00:00:00", "_timestamp": "2013-10-16T10:04:04+00:00", "_updated_at": "2013-10-16T11:04:04.228000", "_week_start_at": "2013-10-14T00:00:00", "for_url": "ga:pagePath=~^/tax-disc$", "unique_visitors": "535" }, { "_id": "2013-10-16T11:02:03+01:00", "_month_start_at": "2013-10-01T00:00:00", "_timestamp": "2013-10-16T10:02:03+00:00", "_updated_at": "2013-10-16T11:02:03.650000", "_week_start_at": "2013-10-14T00:00:00", "for_url": "ga:pagePath=~^/tax-disc$", "unique_visitors": "543" } ] }